Metadata-Version: 2.1
Name: cowEncryption
Version: 0.1
Summary: This library is used for Encryption your code
Home-page: https://github.com/Latip176/cowEncryption
Download-URL: https://github.com/Latip176/cowEncryption/archive/cowEncryption.tar.gz
Author: Muhammad Latif Harkat
Author-email: Muhammad Latif Harkat <latipharkat176@gmail.com>
License: MIT
Project-URL: Homepage, https://github.com/Latip176/cowEncryption
Project-URL: Bug Tracker, https://github.com/Latip176/cowEncryption/issues
Keywords: cowEncryption,Cow Encryption,Python Encryption,Latip176,Encryption,Muhammad Latif Harkat
Classifier: Programming Language :: Python :: 3
Classifier: License :: OSI Approved :: MIT License
Classifier: Operating System :: OS Independent
Requires-Python: >=3.10
License-File: LICENSE
License-File: AUTHORS
